odoo9_addon_l10n_es_aeat-9.0.1.0.6-py2.7-nspkg.pth
odoo9_addon_l10n_es_aeat-9.0.1.0.6.dist-info/DESCRIPTION.rst
odoo9_addon_l10n_es_aeat-9.0.1.0.6.dist-info/METADATA
odoo9_addon_l10n_es_aeat-9.0.1.0.6.dist-info/RECORD
odoo9_addon_l10n_es_aeat-9.0.1.0.6.dist-info/WHEEL
odoo9_addon_l10n_es_aeat-9.0.1.0.6.dist-info/metadata.json
odoo9_addon_l10n_es_aeat-9.0.1.0.6.dist-info/namespace_packages.txt
odoo9_addon_l10n_es_aeat-9.0.1.0.6.dist-info/top_level.txt
odoo_addons/l10n_es_aeat/README.rst
odoo_addons/l10n_es_aeat/__init__.py
odoo_addons/l10n_es_aeat/__openerp__.py
odoo_addons/l10n_es_aeat/data/aeat_partner.xml
odoo_addons/l10n_es_aeat/i18n/bg.po
odoo_addons/l10n_es_aeat/i18n/ca.po
odoo_addons/l10n_es_aeat/i18n/cs.po
odoo_addons/l10n_es_aeat/i18n/en.po
odoo_addons/l10n_es_aeat/i18n/es.po
odoo_addons/l10n_es_aeat/i18n/es_CO.po
odoo_addons/l10n_es_aeat/i18n/es_CR.po
odoo_addons/l10n_es_aeat/i18n/eu.po
odoo_addons/l10n_es_aeat/i18n/fr.po
odoo_addons/l10n_es_aeat/i18n/gl.po
odoo_addons/l10n_es_aeat/i18n/hr.po
odoo_addons/l10n_es_aeat/i18n/nl.po
odoo_addons/l10n_es_aeat/i18n/pl.po
odoo_addons/l10n_es_aeat/i18n/pt.po
odoo_addons/l10n_es_aeat/i18n/pt_BR.po
odoo_addons/l10n_es_aeat/i18n/ru.po
odoo_addons/l10n_es_aeat/i18n/sl.po
odoo_addons/l10n_es_aeat/i18n/sv.po
odoo_addons/l10n_es_aeat/i18n/tr.po
odoo_addons/l10n_es_aeat/i18n/vi.po
odoo_addons/l10n_es_aeat/migrations/9.0.1.0.0/end-migration.py
odoo_addons/l10n_es_aeat/migrations/9.0.1.0.0/pre-migration.py
odoo_addons/l10n_es_aeat/models/__init__.py
odoo_addons/l10n_es_aeat/models/l10n_es_aeat_export_config.py
odoo_addons/l10n_es_aeat/models/l10n_es_aeat_export_config_line.py
odoo_addons/l10n_es_aeat/models/l10n_es_aeat_map_tax.py
odoo_addons/l10n_es_aeat/models/l10n_es_aeat_map_tax_line.py
odoo_addons/l10n_es_aeat/models/l10n_es_aeat_report.py
odoo_addons/l10n_es_aeat/models/l10n_es_aeat_report_tax_mapping.py
odoo_addons/l10n_es_aeat/models/l10n_es_aeat_tax_line.py
odoo_addons/l10n_es_aeat/models/res_partner_bank.py
odoo_addons/l10n_es_aeat/security/aeat_security.xml
odoo_addons/l10n_es_aeat/security/ir.model.access.csv
odoo_addons/l10n_es_aeat/static/description/icon.png
odoo_addons/l10n_es_aeat/static/description/icon_source.svg
odoo_addons/l10n_es_aeat/tests/__init__.py
odoo_addons/l10n_es_aeat/tests/test_l10n_es_aeat.py
