Metadata-Version: 2.0
Name: odoo9-addon-l10n-es-aeat
Version: 9.0.1.0.6
Summary: Modulo base para declaraciones de la AEAT
Home-page: https://odoo-community.org/
Author: Pexego,Acysos,AvanzOSC,Tecnativa,Odoo Community Association (OCA)
Author-email: support@odoo-community.org
License: AGPL-3
Platform: UNKNOWN
Classifier: Programming Language :: Python
Classifier: Framework :: Odoo
Classifier: License :: OSI Approved :: GNU Affero General Public License v3
Requires-Python: ~=2.7
Requires-Dist: odoo (<9.1a,>=9.0a)
Requires-Dist: odoo9-addon-account-tax-balance
Requires-Dist: unidecode
